dayu_widgets/__init__.py
dayu_widgets/__main__.py
dayu_widgets/__version__.py
dayu_widgets/alert.py
dayu_widgets/avatar.py
dayu_widgets/badge.py
dayu_widgets/breadcrumb.py
dayu_widgets/browser.py
dayu_widgets/button_group.py
dayu_widgets/card.py
dayu_widgets/carousel.py
dayu_widgets/check_box.py
dayu_widgets/collapse.py
dayu_widgets/color_palette.py
dayu_widgets/combo_box.py
dayu_widgets/completer.py
dayu_widgets/db_path_buttons.py
dayu_widgets/divider.py
dayu_widgets/dock_widget.py
dayu_widgets/drawer.py
dayu_widgets/field_mixin.py
dayu_widgets/flow_layout.py
dayu_widgets/form.py
dayu_widgets/header_view.py
dayu_widgets/item_model.py
dayu_widgets/item_view.py
dayu_widgets/item_view_full_set.py
dayu_widgets/item_view_set.py
dayu_widgets/label.py
dayu_widgets/line_edit.py
dayu_widgets/line_tab_widget.py
dayu_widgets/loading.py
dayu_widgets/menu.py
dayu_widgets/menu_tab_widget.py
dayu_widgets/message.py
dayu_widgets/mixin.py
dayu_widgets/page.py
dayu_widgets/popup.py
dayu_widgets/progress_bar.py
dayu_widgets/progress_circle.py
dayu_widgets/push_button.py
dayu_widgets/qt/__init__.py
dayu_widgets/radio_button.py
dayu_widgets/sequence_file.py
dayu_widgets/slider.py
dayu_widgets/spin_box.py
dayu_widgets/splitter.py
dayu_widgets/stacked_widget.py
dayu_widgets/static/__init__.py
dayu_widgets/static/add_line.svg
dayu_widgets/static/alert_fill.svg
dayu_widgets/static/alert_line.svg
dayu_widgets/static/app-houdini.png
dayu_widgets/static/app-maya.png
dayu_widgets/static/app-nuke.png
dayu_widgets/static/attachment_line.svg
dayu_widgets/static/avatar.png
dayu_widgets/static/base.json
dayu_widgets/static/big_view.svg
dayu_widgets/static/bold.svg
dayu_widgets/static/calendar_fill.png
dayu_widgets/static/calendar_fill.svg
dayu_widgets/static/calendar_fill_dark.png
dayu_widgets/static/calendar_fill_dark.svg
dayu_widgets/static/calendar_line.png
dayu_widgets/static/calendar_line.svg
dayu_widgets/static/calendar_line_dark.png
dayu_widgets/static/calendar_line_dark.svg
dayu_widgets-1.1.1.dist-info/LICENSE
dayu_widgets-1.1.1.dist-info/METADATA
dayu_widgets-1.1.1.dist-info/WHEEL
dayu_widgets-1.1.1.dist-info/RECORD
