Metadata-Version: 2.3
Name: dayu_widgets
Version: 1.1.1
Summary: Components for PySide2/PySide6.
License: MIT
Keywords: UI,PySide2,PyQt5,PySide6
Author: muyanru
Author-email: muyanru@163.com
Requires-Python: >=3.7,<4.0
Classifier: License :: OSI Approved :: MIT License
Classifier: Programming Language :: Python :: 3
Classifier: Programming Language :: Python :: 3.7
Classifier: Programming Language :: Python :: 3.8
Classifier: Programming Language :: Python :: 3.9
Classifier: Programming Language :: Python :: 3.10
Classifier: Programming Language :: Python :: 3.11
Classifier: Programming Language :: Python :: 3.12
Classifier: Programming Language :: Python :: 3.13
Provides-Extra: pyside2
Provides-Extra: pyside6
Requires-Dist: PySide2 (>=5.15.2.1) ; extra == "pyside2"
Requires-Dist: PySide6 (>=6.4.2) ; extra == "pyside6"
Requires-Dist: qtpy (>=2.3.1,<3.0.0)
Project-URL: Documentation, https://muyr.github.io/dayu_widgets3/#/
Project-URL: Homepage, https://github.com/muyr/dayu_widgets3
Project-URL: Repository, https://github.com/muyr/dayu_widgets3
